{
  "_class": "shapeGroup",
  "clippingMaskMode": 0,
  "do_objectID": "B3F5AB6E-EF81-41E8-A98A-3CFB53671031",
  "exportOptions": {
    "_class": "exportOptions",
    "do_objectID": "2334A4D1-B8BB-4FB0-AD0D-B30BF2879E34",
    "exportFormats": [
    ],
    "includedLayerIds": [
    ],
    "layerOptions": 0,
    "shouldTrim": false
  },
  "frame": {
    "_class": "rect",
    "constrainProportions": false,
    "do_objectID": "B2A71CF9-CA12-4645-AB74-C35E1BF37E6A",
    "height": 19,
    "width": 13,
    "x": 242,
    "y": 312
  },
  "hasClickThrough": false,
  "hasClippingMask": false,
  "isFlippedHorizontal": false,
  "isFlippedVertical": false,
  "isLocked": false,
  "isVisible": true,
  "layerListExpandedType": 1,
  "layers": [
    {
      "class": "shapePath",
      "id": "09AA3ADC-4C6C-4608-BA7D-AB04BE283356"
    }
  ],
  "name": "Shape",
  "nameIsFixed": false,
  "resizingConstraint": 63,
  "resizingType": 0,
  "rotation": 0,
  "shouldBreakMaskChain": false,
  "style": {
    "_class": "style",
    "do_objectID": "8DF7FFDE-FFB3-4ED4-BE11-7F7946699780",
    "endDecorationType": 0,
    "fills": [
      {
        "_class": "fill",
        "color": {
          "_class": "color",
          "alpha": 1,
          "blue": 1,
          "green": 1,
          "red": 1
        },
        "fillType": 0,
        "isEnabled": true,
        "noiseIndex": 0,
        "noiseIntensity": 0,
        "patternFillType": 1,
        "patternTileScale": 1
      }
    ],
    "miterLimit": 10,
    "startDecorationType": 0
  },
  "windingRule": 0
}